{
  "collection": "post",
  "field": "editor_nodes",
  "type": "alias",
  "meta": {
    "collection": "post",
    "conditions": null,
    "display": null,
    "display_options": null,
    "field": "editor_nodes",
    "group": null,
    "hidden": true,
    "interface": null,
    "note": null,
    "options": null,
    "readonly": false,
    "required": false,
    "sort": 16,
    "special": [
      "m2a"
    ],
    "translations": null,
    "validation": null,
    "validation_message": null,
    "width": "full"
  }
}
